bestdori/render/__init__.py
bestdori/render/_utils.py
bestdori/render/config.py
bestdori/render/resources/fonts/TT-Shin Go M.ttf
bestdori/render/resources/skins/skin00_rip/flick.png
bestdori/render/resources/skins/skin00_rip/left.png
bestdori/render/resources/skins/skin00_rip/left_arrow.png
bestdori/render/resources/skins/skin00_rip/long.png
bestdori/render/resources/skins/skin00_rip/right.png
bestdori/render/resources/skins/skin00_rip/right_arrow.png
bestdori/render/resources/skins/skin00_rip/sep.png
bestdori/render/resources/skins/skin00_rip/slide.png
bestdori/render/resources/skins/skin00_rip/tap.png
bestdori/render/resources/skins/skin00_rip/tap_skill.png
bestdori/render/resources/skins/skin00_rip/tap_white.png
bestdori_render-0.1.3.dist-info/METADATA
bestdori_render-0.1.3.dist-info/WHEEL
bestdori_render-0.1.3.dist-info/entry_points.txt
bestdori_render-0.1.3.dist-info/licenses/LICENSE
bestdori_render-0.1.3.dist-info/RECORD
