Metadata-Version: 2.1
Name: bestdori-render
Version: 0.1.3
Summary: Bestdori 谱面渲染工具
Author-Email: zhaomaoniu <2667292003@qq.com>
License: MIT
Requires-Python: >=3.8
Requires-Dist: bestdori-api>=0.2.0
Requires-Dist: Pillow>=10.3.0
